industrio/__init__.py
industrio/config.py
industrio/core.py
industrio-0.1.0.dist-info/METADATA
industrio-0.1.0.dist-info/WHEEL
industrio-0.1.0.dist-info/top_level.txt
industrio-0.1.0.dist-info/RECORD
