Metadata-Version: 2.1
Name: industrio
Version: 0.1.0
Summary: 物联网网关控制与传感器数据读取包
Classifier: Programming Language :: Python :: 3
Classifier: License :: OSI Approved :: MIT License
Classifier: Operating System :: OS Independent
Requires-Python: >=3.6
Requires-Dist: requests>=2.25.0
